uvatradier/__init__.py
uvatradier/account.py
uvatradier/base.py
uvatradier/equity_order.py
uvatradier/market_stream.py
uvatradier/options_data.py
uvatradier/options_order.py
uvatradier/quotes.py
uvatradier/stream.py
uvatradier/tradier.py
uvatradier-0.4.7.dist-info/LICENSE
uvatradier-0.4.7.dist-info/METADATA
uvatradier-0.4.7.dist-info/WHEEL
uvatradier-0.4.7.dist-info/top_level.txt
uvatradier-0.4.7.dist-info/RECORD
