Metadata-Version: 2.1
Name: uvatradier
Version: 0.4.7
Summary: wahoowa
Home-page: https://github.com/thammo4/uvatradier
Author: tom hammons
Project-URL: Bug Tracker, https://github.com/thammo4/uvatradier/issues
Keywords: tradier finance api
License-File: LICENSE
Requires-Dist: requests>=2.0
Requires-Dist: pandas>=1.0
Requires-Dist: matplotlib>=3.0
Requires-Dist: websockets>=8.1
Requires-Dist: asyncio
